pyseoanalyzer/__init__.py
pyseoanalyzer/__main__.py
pyseoanalyzer/analyzer.py
pyseoanalyzer/http.py
pyseoanalyzer/page.py
pyseoanalyzer/stemmer.py
pyseoanalyzer/website.py
pyseoanalyzer/templates/index.html
pyseoanalyzer-2024.4.21.dist-info/METADATA
pyseoanalyzer-2024.4.21.dist-info/WHEEL
pyseoanalyzer-2024.4.21.dist-info/entry_points.txt
pyseoanalyzer-2024.4.21.dist-info/licenses/LICENSE
pyseoanalyzer-2024.4.21.dist-info/RECORD
