Metadata-Version: 2.3
Name: pyseoanalyzer
Version: 2024.4.21
Summary: An SEO tool that analyzes the structure of a site, crawls the site, count words in the body of the site and warns of any technical SEO issues.
Project-URL: Homepage, https://github.com/sethblack/python-seo-analyzer
Project-URL: Repository, https://github.com/sethblack/python-seo-analyzer.git
Project-URL: Issues, https://github.com/sethblack/python-seo-analyzer/issues
Author-email: Seth Black <sblack@sethserver.com>
License: Copyright 2012-2021 Seth Black.
License-File: LICENSE
Keywords: crawler,scraper,search engine optimization,seo,site analyzer,site crawler,site parser,website parser
Classifier: Development Status :: 5 - Production/Stable
Classifier: Environment :: Console
Classifier: Intended Audience :: Developers
Classifier: License :: OSI Approved :: BSD License
Classifier: Operating System :: OS Independent
Classifier: Programming Language :: Python
Classifier: Programming Language :: Python :: 3
Classifier: Programming Language :: Python :: 3 :: Only
Classifier: Topic :: Internet :: WWW/HTTP
Classifier: Topic :: Internet :: WWW/HTTP :: Indexing/Search
Classifier: Topic :: Software Development :: Libraries :: Python Modules
Classifier: Topic :: Text Processing
Requires-Python: >=3.8
Requires-Dist: beautifulsoup4>=4.12.3
Requires-Dist: certifi>=2024.2.2
Requires-Dist: jinja2>=3.1.3
Requires-Dist: lxml>=5.2.1
Requires-Dist: markupsafe>=2.1.5
Requires-Dist: urllib3>=2.2.1
